src/nebari_plugin_metrics_server/__about__.py
src/nebari_plugin_metrics_server/__init__.py
src/nebari_plugin_metrics_server/plugin.py
src/nebari_plugin_metrics_server/template/main.tf
src/nebari_plugin_metrics_server/template/outputs.tf
src/nebari_plugin_metrics_server/template/variables.tf
src/nebari_plugin_metrics_server/template/versions.tf
nebari_plugin_metrics_server-0.0.1.dist-info/METADATA
nebari_plugin_metrics_server-0.0.1.dist-info/WHEEL
nebari_plugin_metrics_server-0.0.1.dist-info/entry_points.txt
nebari_plugin_metrics_server-0.0.1.dist-info/licenses/LICENSE
nebari_plugin_metrics_server-0.0.1.dist-info/RECORD
