Metadata-Version: 2.1
Name: nebari-plugin-metrics-server
Version: 0.0.1
Summary: MetroStar Onyx - Metrics Server plugin for Nebari platform
Project-URL: Documentation, https://github.com/MetroStar/nebari-metrics-server#readme
Project-URL: Issues, https://github.com/MetroStar/nebari-metrics-server/issues
Project-URL: Source, https://github.com/MetroStar/nebari-metrics-server
Author-email: Pedram Adili <padili@metrostar.com>
License-Expression: Apache-2.0
License-File: LICENSE
Classifier: Development Status :: 4 - Beta
Classifier: Programming Language :: Python
Classifier: Programming Language :: Python :: 3.8
Classifier: Programming Language :: Python :: 3.9
Classifier: Programming Language :: Python :: 3.10
Classifier: Programming Language :: Python :: 3.11
Classifier: Programming Language :: Python :: Implementation :: CPython
Classifier: Programming Language :: Python :: Implementation :: PyPy
Requires-Python: >=3.8
Requires-Dist: nebari
